gym_donkeycar/__init__.py
gym_donkeycar/core/__init__.py
gym_donkeycar/core/fps.py
gym_donkeycar/core/tcp_server.py
gym_donkeycar/envs/__init__.py
gym_donkeycar/envs/donkey_env.py
gym_donkeycar/envs/donkey_ex.py
gym_donkeycar/envs/donkey_proc.py
gym_donkeycar/envs/donkey_sim.py
gym_donkeycar-1.0.13.dist-info/AUTHORS.rst
gym_donkeycar-1.0.13.dist-info/LICENSE
gym_donkeycar-1.0.13.dist-info/METADATA
gym_donkeycar-1.0.13.dist-info/WHEEL
gym_donkeycar-1.0.13.dist-info/top_level.txt
gym_donkeycar-1.0.13.dist-info/RECORD
