Metadata-Version: 2.1
Name: gym-donkeycar
Version: 1.0.13
Summary: OpenAI Gym Environments for Donkey Car
Home-page: https://github.com/leigh-johnson/gym-donkeycar
Author: Tawn Kramer
Author-email: leigh@data-literate.com
License: MIT license
Keywords: gym_donkeycar
Platform: UNKNOWN
Classifier: Development Status :: 2 - Pre-Alpha
Classifier: Intended Audience :: Developers
Classifier: License :: OSI Approved :: MIT License
Classifier: Natural Language :: English
Classifier: Programming Language :: Python :: 3.6
Classifier: Programming Language :: Python :: 3.7
Requires-Dist: gym
Requires-Dist: numpy
Requires-Dist: pillow
